.gitignore
LICENSE
README.md
requirements.txt
aescipher/__init__.py
aescipher/cbc.py
aescipher/ctr.py
aescipher/gcm.py
aescipher/utils.py
aescipher-6.0.0.dist-info/LICENSE
aescipher-6.0.0.dist-info/METADATA
aescipher-6.0.0.dist-info/WHEEL
aescipher-6.0.0.dist-info/top_level.txt
aescipher-6.0.0.dist-info/RECORD
