Metadata-Version: 2.1
Name: aescipher
Version: 6.0.0
Summary: Use AES to encrypt everything with ease!
Home-page: https://github.com/foxe6/
Author: f̣ộx̣ệ6
Author-email: foxe6@protonmail.com
License: AGPL-3.0
Project-URL: Sourcecode, https://github.com/foxe6/aescipher
Project-URL: Documentation, https://github.com/foxe6/aescipher/blob/master/test
Project-URL: Example, https://github.com/foxe6/aescipher/blob/master/aescipher/example
Project-URL: Issues, https://github.com/foxe6/aescipher/issues
Project-URL: Funding, https://paypal.me/foxe6
Project-URL: Say Thanks!, https://saythanks.io/to/foxe6
Keywords: aes cipher cbc ctr gcm stream block encrypt decrypt nonce iv file wrapper reader writer
Platform: UNKNOWN
Classifier: Programming Language :: Python :: 3.9
Classifier: Topic :: Utilities
Classifier: Natural Language :: English
Classifier: Intended Audience :: Developers
Classifier: License :: OSI Approved :: GNU Affero General Public License v3
Classifier: Operating System :: MacOS
Classifier: Operating System :: POSIX
Classifier: Operating System :: Microsoft :: Windows :: Windows 10
Classifier: Development Status :: 5 - Production/Stable
Requires-Python: >=3
License-File: LICENSE
